{
	"name": "dataflow_flowlet_demo",
	"properties": {
		"type": "MappingDataFlow",
		"typeProperties": {
			"sources": [
				{
					"dataset": {
						"referenceName": "ds_employee",
						"type": "DatasetReference"
					},
					"name": "source1"
				}
			],
			"sinks": [
				{
					"dataset": {
						"referenceName": "ds_output",
						"type": "DatasetReference"
					},
					"name": "sink1"
				}
			],
			"transformations": [
				{
					"name": "flowlet1",
					"flowlet": {
						"referenceName": "flowlet_demo",
						"type": "DataFlowReference"
					}
				}
			],
			"scriptLines": [
				"source(output(",
				"          EMPLOYEE_ID as string,",
				"          FIRST_NAME as string,",
				"          LAST_NAME as string,",
				"          EMAIL as string,",
				"          PHONE_NUMBER as string,",
				"          HIRE_DATE as string,",
				"          JOB_ID as string,",
				"          SALARY as string,",
				"          COMMISSION_PCT as string,",
				"          MANAGER_ID as string,",
				"          DEPARTMENT_ID as string",
				"     ),",
				"     allowSchemaDrift: true,",
				"     validateSchema: false,",
				"     ignoreNoFilesFound: false,",
				"     partitionBy('hash', 1)) ~> source1",
				"source1 compose(mapColumn(",
				"          DEPARTMENT_ID",
				"     ),",
				"     composition: 'flowlet_demo') ~> flowlet1@(flowetoutput)",
				"flowlet1@flowetoutput sink(allowSchemaDrift: true,",
				"     validateSchema: false,",
				"     input(",
				"          customer_id as string,",
				"          customer_unique_id as string,",
				"          customer_zip_code_prefix as string,",
				"          customer_city as string,",
				"          customer_state as string",
				"     ),",
				"     partitionFileNames:['Flowletexample.csv'],",
				"     skipDuplicateMapInputs: true,",
				"     skipDuplicateMapOutputs: true,",
				"     partitionBy('hash', 1)) ~> sink1"
			]
		}
	}
}